shellescape/__init__.py
shellescape/main.py
shellescape/settings.py
shellescape-3.4.0.dist-info/DESCRIPTION.rst
shellescape-3.4.0.dist-info/METADATA
shellescape-3.4.0.dist-info/pydist.json
shellescape-3.4.0.dist-info/RECORD
shellescape-3.4.0.dist-info/top_level.txt
shellescape-3.4.0.dist-info/WHEEL
