Metadata-Version: 2.0
Name: shellescape
Version: 3.4.0
Summary: Shell escape a string to safely use it as a token in a shell command (backport of Python shlex.quote for Python versions 2.x & < 3.3)
Home-page: https://github.com/chrissimpkins/shellescape
Author: Christopher Simpkins
Author-email: git.simpkins@gmail.com
License: MIT license
Keywords: shell,quote,escape,backport,command line,command,subprocess
Platform: any
Classifier: Development Status :: 5 - Production/Stable
Classifier: Intended Audience :: Developers
Classifier: Natural Language :: English
Classifier: License :: OSI Approved :: MIT License
Classifier: Programming Language :: Python
Classifier: Programming Language :: Python :: 2
Classifier: Programming Language :: Python :: 3
Classifier: Operating System :: MacOS :: MacOS X
Classifier: Operating System :: POSIX
Classifier: Operating System :: Unix
Classifier: Operating System :: Microsoft :: Windows
